storybook/__init__.py
storybook/storybook.py
storybook-0.0.0.dist-info/LICENSE
storybook-0.0.0.dist-info/METADATA
storybook-0.0.0.dist-info/WHEEL
storybook-0.0.0.dist-info/top_level.txt
storybook-0.0.0.dist-info/RECORD
